synopkg/__init__.py
synopkg/cli.py
synopkg-0.1.0.dist-info/METADATA
synopkg-0.1.0.dist-info/WHEEL
synopkg-0.1.0.dist-info/entry_points.txt
synopkg-0.1.0.dist-info/top_level.txt
synopkg-0.1.0.dist-info/RECORD
