Metadata-Version: 2.4
Name: synopkg
Version: 0.1.0
Summary: A Package Manager For Synology by Python3
Author-email: YearnstudioYangyi <yangyi@yearnstudio.cn>
License: MIT
Project-URL: Homepage, https://github.com/yourusername/synopkg
Project-URL: Repository, https://github.com/yourusername/synopkg
Keywords: synology,nas,package-manager,tool
Classifier: Development Status :: 3 - Alpha
Classifier: Intended Audience :: Developers
Classifier: License :: OSI Approved :: MIT License
Classifier: Programming Language :: Python :: 3
Classifier: Programming Language :: Python :: 3.8
Classifier: Programming Language :: Python :: 3.9
Classifier: Programming Language :: Python :: 3.10
Classifier: Programming Language :: Python :: 3.11
Classifier: Programming Language :: Python :: 3.12
Requires-Python: >=3.8
